jetfuelburn/__init__.py
jetfuelburn/breguet.py
jetfuelburn/closedform.py
jetfuelburn/combined.py
jetfuelburn/diagrams.py
jetfuelburn/reducedorder.py
jetfuelburn/statistics.py
jetfuelburn/data/__init__.py
jetfuelburn/data/constants.py
jetfuelburn/data/AIM2015/AIM2015_v11_AircraftPerformanceParams.csv
jetfuelburn/data/AIM2015/__init__.py
jetfuelburn/data/AeroMaps/__init__.py
jetfuelburn/data/AeroMaps/aeromaps_data.csv
jetfuelburn/data/EEA2009/__init__.py
jetfuelburn/data/EEA2009/data.json
jetfuelburn/data/Lee2010/__init__.py
jetfuelburn/data/Lee2010/data_fig_6_fres_const.csv
jetfuelburn/data/PS2025/__init__.py
jetfuelburn/data/PS2025/table_1.csv
jetfuelburn/data/PS2025/table_2.csv
jetfuelburn/data/USDOT/USDOT_data_2013.json
jetfuelburn/data/USDOT/USDOT_data_2018.json
jetfuelburn/data/USDOT/USDOT_data_2024.json
jetfuelburn/data/USDOT/__init__.py
jetfuelburn/figures/__init__.py
jetfuelburn/figures/benchmarking.py
jetfuelburn/figures/realdata.py
jetfuelburn/figures/reducedorder.py
jetfuelburn/utility/__init__.py
jetfuelburn/utility/allocation.py
jetfuelburn/utility/physics.py
jetfuelburn/utility/tests.py
jetfuelburn-1.2.0.dist-info/licenses/LICENSE.txt
jetfuelburn-1.2.0.dist-info/METADATA
jetfuelburn-1.2.0.dist-info/WHEEL
jetfuelburn-1.2.0.dist-info/top_level.txt
jetfuelburn-1.2.0.dist-info/RECORD
