Metadata-Version: 2.4
Name: jetfuelburn
Version: 1.2.0
Summary: A Python package for calculating fuel burn of commercial aircraft.
Author-email: Michael Weinold <michaelphilippweinold+jetfuelburn@gmail.com>
Maintainer-email: Michael Weinold <michaelphilippweinold+jetfuelburn@gmail.com>
License: MIT
Project-URL: source, https://github.com/sustainableaviation/jetfuelburn
Project-URL: homepage, https://jetfuelburn.readthedocs.io
Project-URL: tracker, https://github.com/sustainableaviation/jetfuelburn/issues
Classifier: Development Status :: 5 - Production/Stable
Classifier: Programming Language :: Python
Classifier: Programming Language :: Python :: 3
Classifier: Programming Language :: Python :: 3.10
Classifier: Programming Language :: Python :: 3.11
Classifier: Programming Language :: Python :: 3.12
Classifier: Natural Language :: English
Classifier: Operating System :: OS Independent
Classifier: Topic :: Scientific/Engineering
Requires-Python: >=3.10
License-File: LICENSE.txt
Requires-Dist: pint
Provides-Extra: testing
Requires-Dist: pytest; extra == "testing"
Requires-Dist: pytest-cov; extra == "testing"
Requires-Dist: python-coveralls; extra == "testing"
Dynamic: license-file
